bilbil/__init__.py
bilbil/bilbil.py
bilbil/cli.py
bilbil-0.0.2.dist-info/LICENSE
bilbil-0.0.2.dist-info/METADATA
bilbil-0.0.2.dist-info/WHEEL
bilbil-0.0.2.dist-info/entry_points.txt
bilbil-0.0.2.dist-info/top_level.txt
bilbil-0.0.2.dist-info/RECORD
