Metadata-Version: 2.1
Name: bilbil
Version: 0.0.2
Summary: Bilbil contains all you need to create a perfect package python.
Home-page: https://github.com/wkli/bilbil
Author: Wenkun LI
Author-email: wkunkun.li@gmail.com
License: MIT license
Keywords: bilbil
Platform: UNKNOWN
Classifier: Development Status :: 2 - Pre-Alpha
Classifier: Intended Audience :: Developers
Classifier: License :: OSI Approved :: MIT License
Classifier: Natural Language :: English
Classifier: Programming Language :: Python :: 3
Classifier: Programming Language :: Python :: 3.5
Classifier: Programming Language :: Python :: 3.6
Classifier: Programming Language :: Python :: 3.7
Classifier: Programming Language :: Python :: 3.8
Requires-Python: >=3.5
